[
  {
    "act.name": "Emil Eifrem",
    "NumFilms": 1
  },
  {
    "act.name": "Hugo Weaving",
    "NumFilms": 5
  },
  {
    "act.name": "Laurence Fishburne",
    "NumFilms": 3
  },
  {
    "act.name": "Carrie-Anne Moss",
    "NumFilms": 3
  },
  {
    "act.name": "Keanu Reeves",
    "NumFilms": 7
  },
  {
    "act.name": "Al Pacino",
    "NumFilms": 1
  },
  {
    "act.name": "Charlize Theron",
    "NumFilms": 2
  },
  {
    "act.name": "James Marshall",
    "NumFilms": 1
  },
  {
    "act.name": "Kevin Pollak",
    "NumFilms": 1
  },
  {
    "act.name": "J.T. Walsh",
    "NumFilms": 2
  },
  {
    "act.name": "Aaron Sorkin",
    "NumFilms": 1
  },
  {
    "act.name": "Cuba Gooding Jr.",
    "NumFilms": 4
  },
  {
    "act.name": "Christopher Guest",
    "NumFilms": 1
  },
  {
    "act.name": "Noah Wyle",
    "NumFilms": 1
  },
  {
    "act.name": "Kiefer Sutherland",
    "NumFilms": 2
  },
  {
    "act.name": "Kevin Bacon",
    "NumFilms": 3
  },
  {
    "act.name": "Demi Moore",
    "NumFilms": 1
  },
  {
    "act.name": "Jack Nicholson",
    "NumFilms": 5
  },
  {
    "act.name": "Tom Cruise",
    "NumFilms": 3
  },
  {
    "act.name": "Val Kilmer",
    "NumFilms": 1
  },
  {
    "act.name": "Meg Ryan",
    "NumFilms": 5
  },
  {
    "act.name": "Tom Skerritt",
    "NumFilms": 1
  },
  {
    "act.name": "Kelly McGillis",
    "NumFilms": 1
  },
  {
    "act.name": "Anthony Edwards",
    "NumFilms": 1
  },
  {
    "act.name": "Jerry O'Connell",
    "NumFilms": 2
  },
  {
    "act.name": "Bonnie Hunt",
    "NumFilms": 2
  },
  {
    "act.name": "Jay Mohr",
    "NumFilms": 1
  },
  {
    "act.name": "Jonathan Lipnicki",
    "NumFilms": 1
  },
  {
    "act.name": "Renee Zellweger",
    "NumFilms": 1
  },
  {
    "act.name": "Kelly Preston",
    "NumFilms": 1
  },
  {
    "act.name": "Regina King",
    "NumFilms": 1
  },
  {
    "act.name": "River Phoenix",
    "NumFilms": 1
  },
  {
    "act.name": "Marshall Bell",
    "NumFilms": 2
  },
  {
    "act.name": "Wil Wheaton",
    "NumFilms": 1
  },
  {
    "act.name": "John Cusack",
    "NumFilms": 1
  },
  {
    "act.name": "Corey Feldman",
    "NumFilms": 1
  },
  {
    "act.name": "Helen Hunt",
    "NumFilms": 3
  },
  {
    "act.name": "Greg Kinnear",
    "NumFilms": 2
  },
  {
    "act.name": "Robin Williams",
    "NumFilms": 3
  },
  {
    "act.name": "Max von Sydow",
    "NumFilms": 2
  },
  {
    "act.name": "Werner Herzog",
    "NumFilms": 1
  },
  {
    "act.name": "Annabella Sciorra",
    "NumFilms": 1
  },
  {
    "act.name": "Ethan Hawke",
    "NumFilms": 1
  },
  {
    "act.name": "Rick Yune",
    "NumFilms": 2
  },
  {
    "act.name": "James Cromwell",
    "NumFilms": 2
  },
  {
    "act.name": "Tom Hanks",
    "NumFilms": 12
  },
  {
    "act.name": "Parker Posey",
    "NumFilms": 1
  },
  {
    "act.name": "Steve Zahn",
    "NumFilms": 2
  },
  {
    "act.name": "Dave Chappelle",
    "NumFilms": 1
  },
  {
    "act.name": "Victor Garber",
    "NumFilms": 1
  },
  {
    "act.name": "Bill Pullman",
    "NumFilms": 1
  },
  {
    "act.name": "Rita Wilson",
    "NumFilms": 1
  },
  {
    "act.name": "Rosie O'Donnell",
    "NumFilms": 2
  },
  {
    "act.name": "Nathan Lane",
    "NumFilms": 2
  },
  {
    "act.name": "Carrie Fisher",
    "NumFilms": 1
  },
  {
    "act.name": "Billy Crystal",
    "NumFilms": 1
  },
  {
    "act.name": "Bruno Kirby",
    "NumFilms": 1
  },
  {
    "act.name": "Liv Tyler",
    "NumFilms": 1
  },
  {
    "act.name": "Brooke Langton",
    "NumFilms": 1
  },
  {
    "act.name": "Orlando Jones",
    "NumFilms": 1
  },
  {
    "act.name": "Gene Hackman",
    "NumFilms": 3
  },
  {
    "act.name": "Zach Grenier",
    "NumFilms": 2
  },
  {
    "act.name": "Christian Bale",
    "NumFilms": 1
  },
  {
    "act.name": "Clint Eastwood",
    "NumFilms": 1
  },
  {
    "act.name": "Richard Harris",
    "NumFilms": 1
  },
  {
    "act.name": "Ice-T",
    "NumFilms": 1
  },
  {
    "act.name": "Dina Meyer",
    "NumFilms": 1
  },
  {
    "act.name": "Takeshi Kitano",
    "NumFilms": 1
  },
  {
    "act.name": "Jim Broadbent",
    "NumFilms": 1
  },
  {
    "act.name": "Halle Berry",
    "NumFilms": 1
  },
  {
    "act.name": "Ian McKellen",
    "NumFilms": 1
  },
  {
    "act.name": "Audrey Tautou",
    "NumFilms": 1
  },
  {
    "act.name": "Paul Bettany",
    "NumFilms": 1
  },
  {
    "act.name": "John Hurt",
    "NumFilms": 1
  },
  {
    "act.name": "Stephen Rea",
    "NumFilms": 1
  },
  {
    "act.name": "Natalie Portman",
    "NumFilms": 1
  },
  {
    "act.name": "Ben Miles",
    "NumFilms": 3
  },
  {
    "act.name": "Emile Hirsch",
    "NumFilms": 1
  },
  {
    "act.name": "Rain",
    "NumFilms": 2
  },
  {
    "act.name": "Christina Ricci",
    "NumFilms": 1
  },
  {
    "act.name": "Susan Sarandon",
    "NumFilms": 1
  },
  {
    "act.name": "John Goodman",
    "NumFilms": 1
  },
  {
    "act.name": "Matthew Fox",
    "NumFilms": 1
  },
  {
    "act.name": "Naomie Harris",
    "NumFilms": 1
  },
  {
    "act.name": "Sam Rockwell",
    "NumFilms": 2
  },
  {
    "act.name": "Patricia Clarkson",
    "NumFilms": 1
  },
  {
    "act.name": "Michael Clarke Duncan",
    "NumFilms": 1
  },
  {
    "act.name": "David Morse",
    "NumFilms": 1
  },
  {
    "act.name": "Gary Sinise",
    "NumFilms": 2
  },
  {
    "act.name": "Michael Sheen",
    "NumFilms": 1
  },
  {
    "act.name": "Frank Langella",
    "NumFilms": 1
  },
  {
    "act.name": "Oliver Platt",
    "NumFilms": 2
  },
  {
    "act.name": "John C. Reilly",
    "NumFilms": 1
  },
  {
    "act.name": "Danny DeVito",
    "NumFilms": 2
  },
  {
    "act.name": "Ed Harris",
    "NumFilms": 1
  },
  {
    "act.name": "Bill Paxton",
    "NumFilms": 3
  },
  {
    "act.name": "Philip Seymour Hoffman",
    "NumFilms": 2
  },
  {
    "act.name": "Diane Keaton",
    "NumFilms": 1
  },
  {
    "act.name": "Julia Roberts",
    "NumFilms": 1
  },
  {
    "act.name": "Madonna",
    "NumFilms": 1
  },
  {
    "act.name": "Geena Davis",
    "NumFilms": 1
  },
  {
    "act.name": "Lori Petty",
    "NumFilms": 1
  }
]